{
  "name": "28cdcab1-66c7-41af-a9b0-023d8de03f75",
  "tags": [ "#switchflows", "#account", "#replacecard", "#points" ],
  "displayName": "Error handling - Switch flows from replace card to check loyalty points after login",
  "testCaseConversationTurns": [ {
    "userInput": {
      "isWebhookEnabled": true,
      "input": {
        "text": {
          "text": "I lost my loyalty card"
        },
        "languageCode": "en"
      }
    },
    "virtualAgentOutput": {
      "sessionParameters": {
        "allow_guest_login": false,
        "has_welcomed_user": true,
        "is_returning": true,
        "operation": "Replace Card",
        "operation_complete": false
      },
      "triggeredIntent": {
        "name": "retail.replace_loyalty_card_initiate"
      },
      "currentPage": {
        "name": "Clarify Phone Number",
        "flow": "User Verification Flow"
      },
      "textResponses": [ {
        "text": [ "First, let me verify your account details." ]
      }, {
        "text": [ "Is the phone number on your account the same as the one you're calling in from?" ]
      } ],
      "currentFlow": {
        "name": "User Verification Flow"
      }
    }
  }, {
    "userInput": {
      "isWebhookEnabled": true,
      "input": {
        "text": {
          "text": "Yes"
        },
        "languageCode": "en"
      }
    },
    "virtualAgentOutput": {
      "sessionParameters": {
        "allow_guest_login": false,
        "has_welcomed_user": true,
        "is_returning": true,
        "operation": "Replace Card",
        "operation_complete": false
      },
      "triggeredIntent": {
        "name": "small_talk.confirmation.yes"
      },
      "currentPage": {
        "name": "Request to send PIN",
        "flow": "User Verification Flow"
      },
      "textResponses": [ {
        "text": [ "Alright, I've verified your phone number." ]
      }, {
        "text": [ "I'll need to send you a PIN to authenticate you. Would you like me to send it? Standard message charges may apply." ]
      } ],
      "currentFlow": {
        "name": "User Verification Flow"
      }
    }
  }, {
    "userInput": {
      "isWebhookEnabled": true,
      "input": {
        "text": {
          "text": "Yes"
        },
        "languageCode": "en"
      }
    },
    "virtualAgentOutput": {
      "sessionParameters": {
        "allow_guest_login": false,
        "has_welcomed_user": true,
        "is_returning": true,
        "operation": "Replace Card",
        "operation_complete": false
      },
      "triggeredIntent": {
        "name": "small_talk.confirmation.yes"
      },
      "currentPage": {
        "name": "Collect PIN",
        "flow": "User Verification Flow"
      },
      "textResponses": [ {
        "text": [ "I have sent a 4 digit PIN to your phone." ]
      }, {
        "text": [ "Could you please give me the PIN you received? You can say it or enter it into the keypad." ]
      } ],
      "currentFlow": {
        "name": "User Verification Flow"
      }
    }
  }, {
    "userInput": {
      "isWebhookEnabled": true,
      "input": {
        "text": {
          "text": "4529"
        },
        "languageCode": "en"
      }
    },
    "virtualAgentOutput": {
      "sessionParameters": {
        "has_welcomed_user": true,
        "is_guest": false,
        "is_logged_in": true,
        "is_returning": true,
        "operation_complete": false,
        "pin_number": "4529"
      },
      "currentPage": {
        "name": "Verify Delivery Address",
        "flow": "Card Replacement Flow"
      },
      "textResponses": [ {
        "text": [ "Thank you! I have verified your account." ]
      }, {
        "text": [ "Before I can send a replacement card, I'll need to verify your delivery address. Is your address still 1600 Amphitheatre Parkway, Mountain View, CA 94043?" ]
      } ],
      "currentFlow": {
        "name": "Card Replacement Flow"
      }
    }
  }, {
    "userInput": {
      "isWebhookEnabled": true,
      "input": {
        "text": {
          "text": "How many loyalty points do I have"
        },
        "languageCode": "en"
      }
    },
    "virtualAgentOutput": {
      "sessionParameters": {
        "has_completed_one_operation": true,
        "has_welcomed_user": true,
        "is_guest": false,
        "is_logged_in": true,
        "is_returning": false,
        "operation_complete": false,
        "pin_number": "4529"
      },
      "triggeredIntent": {
        "name": "retail.account_loyalty_points_initiate"
      },
      "currentPage": {
        "name": "Main Menu",
        "flow": "Default Start Flow"
      },
      "textResponses": [ {
        "text": [ "Your account has 2200 loyalty points." ]
      }, {
        "text": [ "Can I help you with anything else?" ]
      } ],
      "currentFlow": {
        "name": "Default Start Flow"
      }
    }
  }, {
    "userInput": {
      "isWebhookEnabled": true,
      "input": {
        "text": {
          "text": "No thank you"
        },
        "languageCode": "en"
      }
    },
    "virtualAgentOutput": {
      "sessionParameters": {
        "has_completed_one_operation": true,
        "has_welcomed_user": true,
        "is_guest": false,
        "is_logged_in": true,
        "is_returning": false,
        "operation_complete": false,
        "pin_number": "4529"
      },
      "triggeredIntent": {
        "name": "small_talk.confirmation.no"
      },
      "currentPage": {
        "name": "End Session",
        "flow": "Default Start Flow"
      },
      "textResponses": [ {
        "text": [ "In that case, thank you for calling. Goodbye!" ]
      } ],
      "currentFlow": {
        "name": "Default Start Flow"
      }
    }
  } ],
  "creationTime": {
    "seconds": 1607502348,
    "nanos": 254779000
  }
}
